[
    {
        "2024-08-08": [
            0.5574,
            0.48465,
            0.4588,
            0.5602,
            0.49895,
            0.4994,
            0.47115,
            0.7452000000000001,
            0.50845,
            0.2888,
            0.6369,
            0.49365000000000003,
            0.1376
        ],
        "2024-08-07": [
            0.49985,
            0.66935,
            0.4956,
            -0.23685,
            0.31845,
            0.431,
            0.77885,
            0.31245
        ],
        "2024-08-06": [
            -0.0774,
            0.4997,
            0.4934,
            0.0516,
            0.0,
            0.4738,
            0.5,
            0.0,
            0.85205,
            0.79945,
            -0.4951,
            0.0,
            0.4088,
            0.37985,
            -0.2294,
            0.67325
        ],
        "2024-08-05": [
            0.482,
            0.4045,
            0.6299,
            0.75475,
            0.683,
            0.81395,
            0.41785,
            -0.148,
            0.23835,
            0.148
        ],
        "2024-08-04": [
            0.4917
        ],
        "2024-08-02": [
            0.7268,
            0.64615,
            0.75525,
            0.7631,
            0.8148500000000001,
            0.31525000000000003,
            0.7354,
            0.26335
        ],
        "2024-08-01": [
            0.49965,
            0.49965,
            0.4981,
            0.5998,
            0.21075,
            0.3389
        ],
        "2024-07-31": [
            0.82395,
            0.75495,
            0.35645000000000004,
            0.12055
        ],
        "2024-07-30": [
            0.4966,
            0.49055,
            0.0,
            0.51085,
            0.07655
        ],
        "2024-07-29": [
            0.70645,
            0.49945,
            0.8231999999999999,
            0.6315999999999999,
            0.3764,
            -0.15075000000000002
        ],
        "2024-07-28": [
            0.7008,
            0.5362,
            0.48805
        ],
        "2024-07-26": [
            0.81765,
            0.4993,
            0.4986,
            0.3496,
            0.53805,
            0.87095,
            0.67465,
            0.17629999999999998,
            0.50795,
            0.26335,
            0.7076,
            0.30575
        ],
        "2024-07-25": [
            0.73805,
            0.49235,
            0.8350500000000001,
            0.54895
        ],
        "2024-07-24": [
            0.49595,
            0.4994,
            0.73655,
            0.7926,
            0.49605,
            0.69955,
            0.3941,
            -0.10115,
            0.3548,
            0.4019
        ],
        "2024-07-23": [
            0.4983,
            0.49885,
            0.4994,
            0.6907,
            0.5514,
            0.4467,
            0.1591,
            0.4037
        ],
        "2024-07-22": [
            0.6666,
            0.3841,
            0.49975,
            0.1806
        ],
        "2024-07-21": [
            0.4995
        ],
        "2024-07-20": [
            0.72,
            0.4939,
            0.49975,
            0.3825
        ],
        "2024-07-19": [
            0.74655,
            0.7188,
            0.55165,
            0.44789999999999996,
            0.45855
        ],
        "2024-07-18": [
            0.41135,
            0.43435,
            0.71855,
            0.66845,
            0.0,
            0.66995,
            0.4998,
            0.46965,
            0.29500000000000004,
            0.25880000000000003,
            0.3243,
            0.0
        ],
        "2024-07-17": [
            0.49605,
            0.5423,
            0.50995,
            0.49975,
            0.4994,
            0.11035,
            0.2202,
            0.17,
            0.0
        ],
        "2024-07-16": [
            0.5881,
            0.6669,
            0.064,
            0.47395,
            0.14135000000000003,
            0.79205,
            0.31845,
            -0.02200000000000002,
            0.30915000000000004
        ],
        "2024-07-15": [
            0.125,
            0.49925,
            0.29295,
            0.0
        ],
        "2024-07-14": [
            0.49845,
            0.7464,
            0.64755,
            0.24695
        ],
        "2024-07-13": [
            0.49845,
            0.43555,
            0.4991,
            0.5904,
            0.2908
        ],
        "2024-07-12": [
            0.7921,
            0.3062,
            0.8583000000000001,
            0.65185,
            0.36755,
            0.65215
        ],
        "2024-07-11": [
            0.8176,
            0.36345,
            0.49985,
            0.4994,
            0.08254999999999998,
            0.6904,
            0.87015,
            0.49955,
            0.89445,
            0.36345,
            0.31245,
            0.2202
        ],
        "2024-07-10": [
            0.38075000000000003,
            0.49925,
            0.499,
            0.71885,
            0.6845,
            0.68,
            0.0
        ],
        "2024-07-09": [
            0.66695,
            0.49905,
            0.4997,
            0.76325,
            0.8239,
            0.8177000000000001,
            0.4996,
            0.4995,
            0.37895,
            0.6492,
            0.28595
        ],
        "2024-07-08": [
            0.49935,
            0.49925,
            0.9097999999999999,
            0.0,
            0.7376,
            0.6369,
            0.24695,
            0.0
        ],
        "2024-07-07": [
            0.61165
        ],
        "2024-07-06": [
            0.73735
        ],
        "2024-07-05": [
            0.0,
            0.18645,
            0.4995,
            0.53755,
            0.4996,
            0.6698000000000001,
            0.49615,
            0.6362,
            0.1806,
            -0.2113
        ],
        "2024-07-04": [
            0.69035,
            0.7840499999999999,
            0.4995,
            0.26335,
            0.7605999999999999
        ],
        "2024-07-03": [
            0.4994,
            0.35755000000000003,
            0.33955,
            0.4991,
            -0.1591,
            0.1909
        ],
        "2024-07-02": [
            0.4957,
            0.49365,
            -0.20095
        ],
        "2024-07-01": [
            0.5757,
            0.6123
        ],
        "2024-06-30": [
            0.6583,
            0.7921
        ],
        "2024-06-29": [
            0.7381500000000001,
            0.7335
        ],
        "2024-06-28": [
            0.83465,
            0.4992,
            0.8963
        ],
        "2024-06-27": [
            0.4998,
            0.49935,
            0.49715,
            0.6908,
            0.79895,
            0.84465,
            0.7777000000000001,
            0.5501,
            0.2202,
            0.685,
            0.148
        ],
        "2024-06-26": [
            0.66735,
            0.28855,
            0.16455,
            0.4037
        ],
        "2024-06-25": [
            0.4987,
            0.60015,
            0.49875,
            0.0
        ],
        "2024-06-24": [
            0.8141499999999999,
            0.8120499999999999,
            0.8908,
            0.05435000000000004
        ],
        "2024-06-23": [
            0.5507,
            0.90085,
            0.4994,
            0.49895
        ],
        "2024-06-22": [
            0.6779000000000001,
            0.17675000000000002,
            0.861,
            -0.3272
        ],
        "2024-06-21": [
            0.4996,
            0.66955,
            0.3849,
            0.5752,
            0.49985,
            0.55315,
            0.21075
        ],
        "2024-06-20": [
            0.498,
            0.49765,
            0.49905,
            0.49965,
            0.49855,
            0.48695,
            0.6239,
            0.89325,
            0.7487,
            0.3953,
            0.41355,
            0.0,
            0.148,
            -0.13775
        ],
        "2024-06-19": [
            0.29625,
            0.3843,
            0.3548,
            0.1913
        ],
        "2024-06-18": [
            0.69045,
            0.6228,
            0.5998,
            0.09299999999999997,
            0.49905,
            -0.41390000000000005,
            -0.3449,
            0.5786
        ],
        "2024-06-17": [
            0.8577,
            0.8694500000000001,
            0.49935,
            0.61195,
            0.6752,
            0.74675,
            0.1591
        ],
        "2024-06-16": [
            0.73805
        ],
        "2024-06-15": [
            0.49955,
            0.85785,
            0.3062,
            0.31845
        ],
        "2024-06-14": [
            0.81755,
            0.46075,
            0.49915,
            0.72905,
            0.6356999999999999,
            0.23835,
            0.0864,
            0.72475
        ],
        "2024-06-13": [
            0.49815,
            0.30874999999999997,
            0.64695,
            -0.22949999999999998,
            -0.2202
        ],
        "2024-06-12": [
            0.6673,
            0.69045,
            0.4991,
            0.555,
            0.69035,
            0.49975,
            0.4995,
            0.69035,
            -0.3057,
            0.3753,
            0.45424999999999993,
            0.29295
        ],
        "2024-06-11": [
            0.49135,
            0.67805,
            0.647,
            0.79955,
            0.63185,
            0.11235,
            0.41000000000000003,
            0.57755
        ],
        "2024-06-10": [
            0.85455,
            0.7922,
            0.7611,
            -0.36725,
            0.07185,
            0.74705,
            0.29295
        ],
        "2024-06-09": [
            0.13954999999999998
        ],
        "2024-06-08": [
            0.35114999999999996
        ],
        "2024-06-07": [
            0.39225,
            0.6905,
            0.8626499999999999,
            0.24425,
            0.4996,
            0.7632,
            0.0,
            0.3715,
            0.6571499999999999
        ],
        "2024-06-06": [
            0.19849999999999995,
            0.7627999999999999,
            0.4987,
            0.72855,
            0.73765,
            0.5381,
            0.45594999999999997,
            0.4158
        ],
        "2024-06-05": [
            0.49975,
            0.3496,
            0.6905,
            0.49835,
            0.69035,
            0.74615,
            0.012399999999999994,
            0.11315,
            0.012399999999999994
        ],
        "2024-06-04": [
            0.73765,
            0.9004000000000001,
            0.10115
        ],
        "2024-06-03": [
            0.27865000000000006,
            0.45735
        ],
        "2024-06-02": [
            0.4984
        ],
        "2024-06-01": [
            0.03585000000000002
        ],
        "2024-05-31": [
            0.7193499999999999,
            0.824,
            0.49975,
            0.73245,
            0.73725,
            0.26335,
            0.26335
        ],
        "2024-05-30": [
            0.8651,
            0.49925,
            0.76295,
            0.5382,
            0.83965,
            0.29864999999999997,
            0.87755,
            0.49925,
            -0.2825,
            0.1909,
            0.0386,
            -0.12439999999999998,
            0.27885
        ],
        "2024-05-29": [
            0.49885,
            0.5865,
            0.4949,
            0.4987,
            0.4948,
            0.11315,
            -0.0386
        ],
        "2024-05-28": [
            0.49955,
            0.49915,
            0.64635,
            0.7437,
            0.7535000000000001,
            0.0,
            0.58245,
            0.63005
        ],
        "2024-05-27": [
            0.7199,
            0.3944,
            0.50615
        ],
        "2024-05-26": [
            0.7241500000000001
        ],
        "2024-05-25": [
            0.401
        ],
        "2024-05-24": [
            -0.3057,
            0.49865,
            0.49935,
            0.4995,
            0.26025,
            0.8667499999999999,
            0.4905,
            0.6561,
            0.53755,
            0.31845,
            0.25115
        ],
        "2024-05-23": [
            0.4992,
            0.3852,
            0.21764999999999998
        ],
        "2024-05-22": [
            0.7195,
            0.41074999999999995,
            0.8628,
            0.49725,
            0.48785,
            -0.3359,
            0.6577,
            0.33525
        ],
        "2024-05-21": [
            0.49785,
            0.70035,
            0.7988999999999999,
            0.4993,
            0.4987,
            0.79255,
            0.4949,
            0.0386,
            0.20095,
            0.0,
            0.0
        ],
        "2024-05-20": [
            0.32985,
            0.69075,
            0.6,
            0.7607999999999999,
            0.2143,
            0.6772,
            -0.17
        ],
        "2024-05-19": [
            0.76215,
            0.49855
        ],
        "2024-05-18": [
            0.7382,
            0.612
        ],
        "2024-05-17": [
            0.8579,
            0.74575,
            0.2463,
            0.148
        ],
        "2024-05-16": [
            0.6872,
            0.74655,
            0.4992,
            0.49905,
            0.6605,
            0.2294
        ],
        "2024-05-15": [
            0.49275,
            0.25734999999999997,
            0.49455,
            -0.36725,
            -0.1372
        ],
        "2024-05-14": [
            0.82395,
            0.44784999999999997,
            0.34045000000000003,
            0.4999,
            0.3298,
            0.36345,
            0.22485,
            -0.1333,
            0.11865,
            0.148
        ],
        "2024-05-13": [
            0.81835,
            -0.3808,
            0.49925,
            -0.19615
        ],
        "2024-05-12": [
            0.48595,
            0.5677,
            0.49885,
            0.49975,
            0.3243,
            0.3825,
            0.15710000000000002
        ],
        "2024-05-11": [
            0.71575,
            -0.3272,
            0.7375499999999999
        ],
        "2024-05-10": [
            0.4993,
            0.6354,
            -0.3808,
            -0.0386,
            -0.21075
        ],
        "2024-05-09": [
            0.29880000000000007,
            0.43585,
            -0.3808,
            0.12689999999999999,
            -0.4019
        ],
        "2024-05-08": [
            0.49895,
            0.49885,
            -0.59525,
            0.59715,
            0.8182,
            0.23905,
            0.49105,
            0.4995,
            0.2787,
            0.7342500000000001,
            -0.24695,
            -0.43035,
            0.0,
            0.07655
        ],
        "2024-05-07": [
            0.60895,
            0.38234999999999997,
            0.64985,
            0.8173,
            0.4931,
            0.82755,
            0.6884,
            0.5804,
            0.4278,
            0.33225,
            0.49835,
            0.8369,
            0.49735,
            0.83995,
            -0.62685,
            0.5,
            0.2231,
            0.20095,
            0.4215,
            0.49415,
            0.81785,
            -0.22694999999999999,
            0.0,
            0.7529,
            -0.21075
        ],
        "2024-05-06": [
            0.49735,
            0.49955,
            0.49785,
            0.5106,
            0.2202,
            0.608,
            0.60845,
            0.7858,
            0.70075,
            0.0,
            0.38585,
            0.4691,
            0.31845,
            -0.1692,
            0.07655
        ],
        "2024-05-05": [
            0.5377,
            0.4063,
            0.49555
        ],
        "2024-05-04": [
            0.49955
        ],
        "2024-05-03": [
            0.72565,
            0.7486999999999999,
            0.7376,
            0.49955,
            0.1591
        ],
        "2024-05-02": [
            0.49965,
            0.8535,
            -0.12674999999999997,
            0.0,
            0.0,
            -0.6381
        ],
        "2024-05-01": [
            0.6662,
            0.49955,
            0.49905,
            0.49785,
            0.73685,
            0.35515,
            0.7631,
            0.7122999999999999,
            0.28595,
            0.0,
            0.4221
        ],
        "2024-04-30": [
            0.4993,
            0.5996,
            0.4983,
            0.28615
        ],
        "2024-04-29": [
            0.49945,
            -0.3808,
            0.7375499999999999,
            0.4991,
            0.2997
        ],
        "2024-04-28": [
            0.70045
        ],
        "2024-04-27": [
            0.67995,
            0.56645
        ],
        "2024-04-26": [
            0.4993,
            0.4997,
            0.6005,
            0.44425,
            0.10115,
            0.3243,
            0.46035000000000004,
            0.15355
        ],
        "2024-04-25": [
            0.8891,
            0.43535,
            0.27125,
            0.0
        ],
        "2024-04-24": [
            0.4971,
            0.6116,
            0.6242,
            0.48579999999999995,
            0.4994,
            0.13895,
            0.5705,
            0.0386
        ],
        "2024-04-23": [
            0.49885,
            0.49925,
            0.82395,
            0.75505,
            0.35130000000000006,
            0.6234500000000001,
            0.4994,
            0.7927,
            0.38634999999999997,
            -0.23835,
            0.125,
            0.0
        ],
        "2024-04-22": [
            0.5883,
            0.9477500000000001,
            0.8160499999999999,
            0.918
        ],
        "2024-04-21": [
            0.69075,
            0.81455,
            0.79945,
            0.90335,
            0.3062
        ],
        "2024-04-20": [
            0.49895,
            -0.05165
        ],
        "2024-04-19": [
            0.49935,
            0.7375499999999999,
            0.6899,
            0.49935,
            0.21205000000000002,
            0.85015,
            0.87825,
            0.14180000000000004
        ],
        "2024-04-18": [
            0.15945000000000004,
            -0.3272,
            0.3656,
            -0.25144999999999995
        ],
        "2024-04-17": [
            0.4998,
            0.4063,
            -0.3548,
            0.14434999999999998,
            0.90765,
            0.3986,
            0.051500000000000004,
            0.21075
        ],
        "2024-04-16": [
            0.4961,
            0.49935,
            0.8184
        ],
        "2024-04-15": [
            0.49985,
            0.9465,
            0.4992,
            0.7381,
            0.0,
            0.3753,
            0.0
        ],
        "2024-04-14": [
            0.9357500000000001,
            0.49955
        ],
        "2024-04-13": [
            0.73785,
            0.34065,
            0.7991,
            -0.2841
        ],
        "2024-04-12": [
            0.7194,
            0.6456999999999999,
            0.49975,
            0.3451,
            0.3592,
            0.5656
        ],
        "2024-04-11": [
            0.21075,
            0.49725,
            0.0
        ],
        "2024-04-10": [
            0.5995,
            0.4997,
            0.4572
        ],
        "2024-04-09": [
            0.7926,
            0.73605,
            0.48385
        ],
        "2024-04-08": [
            0.49865,
            0.71945,
            0.49895,
            0.4981,
            0.49915,
            0.47065,
            0.49385,
            0.81775,
            -0.19615,
            0.30555,
            0.4111,
            0.10115,
            -0.3062,
            0.17
        ],
        "2024-04-07": [
            0.38575000000000004,
            0.385
        ],
        "2024-04-06": [
            0.4985,
            -0.3808
        ],
        "2024-04-05": [
            0.5885,
            -0.3057,
            0.79945,
            0.1806
        ],
        "2024-04-04": [
            0.2997,
            0.6285,
            0.0386,
            0.28914999999999996,
            0.148
        ],
        "2024-04-03": [
            0.26335
        ],
        "2024-04-01": [
            0.49595,
            0.6791
        ],
        "2024-03-31": [
            0.4997,
            0.7361,
            0.73795
        ],
        "2024-03-29": [
            -0.28595,
            0.33765,
            0.54025,
            0.49675,
            0.7378,
            0.4158,
            0.6535
        ],
        "2024-03-28": [
            0.20095,
            0.23835,
            0.5975,
            0.4999,
            0.7968500000000001,
            0.3825,
            -0.2535,
            0.3592
        ],
        "2024-03-27": [
            0.4992,
            0.28945,
            -0.4869
        ],
        "2024-03-26": [
            0.24455,
            0.6337999999999999,
            0.6471,
            0.75135,
            0.5416,
            0.3062
        ],
        "2024-03-25": [
            0.4969,
            -0.1273,
            0.4994,
            0.3295,
            -0.08499999999999999,
            0.62225
        ],
        "2024-03-24": [
            0.82355
        ],
        "2024-03-23": [
            0.64525
        ],
        "2024-03-22": [
            0.46375,
            0.34075,
            0.7547,
            0.6459,
            0.91515,
            0.66905,
            0.24695,
            0.11205000000000001,
            0.30565000000000003
        ],
        "2024-03-21": [
            -0.6711499999999999,
            0.8571500000000001
        ],
        "2024-03-20": [
            0.4997,
            0.736,
            0.49365,
            0.5637,
            0.1509,
            -0.148,
            0.6605
        ],
        "2024-03-19": [
            0.4975,
            -0.36995,
            0.49245,
            0.62085,
            0.28595
        ],
        "2024-03-18": [
            0.8239,
            0.4997,
            -0.3548,
            0.4994,
            0.79935,
            0.0,
            -0.20095
        ],
        "2024-03-17": [
            0.49945,
            0.49905
        ],
        "2024-03-16": [
            0.85885,
            0.96195,
            0.5449499999999999,
            -0.030949999999999978
        ],
        "2024-03-15": [
            0.4933,
            0.7375499999999999,
            0.525,
            0.9027000000000001,
            0.12689999999999999
        ],
        "2024-03-14": [
            0.49985,
            0.37570000000000003,
            0.7363500000000001,
            0.7369,
            0.2997,
            -0.10115,
            -0.20095,
            -0.2423
        ],
        "2024-03-13": [
            0.5418499999999999,
            0.41145,
            0.4997,
            0.23609999999999998,
            0.6184000000000001,
            0.7862,
            0.2516
        ],
        "2024-03-12": [
            0.7468,
            0.4088,
            0.65915
        ],
        "2024-03-11": [
            0.4995,
            0.71655,
            0.86115,
            0.8785000000000001,
            0.08275,
            0.43125,
            0.4037
        ],
        "2024-03-10": [
            0.6128,
            0.6369,
            0.13115
        ],
        "2024-03-09": [
            0.4982,
            0.53525
        ],
        "2024-03-08": [
            0.49965,
            0.5998,
            0.69075,
            0.41355,
            0.1909,
            0.1591
        ],
        "2024-03-07": [
            0.60005,
            0.46715,
            0.5235,
            -0.1628,
            0.148,
            0.4687,
            0.0258
        ],
        "2024-03-06": [
            0.838,
            0.39994999999999997,
            0.4994,
            0.49465,
            0.79915,
            0.4911,
            -0.01305,
            0.76285,
            0.73705,
            0.7381,
            0.27885,
            -0.21075
        ],
        "2024-03-05": [
            0.85875,
            0.4962,
            0.8404,
            0.23835
        ],
        "2024-03-04": [
            0.3517,
            0.49925,
            0.4934,
            0.70075,
            0.79905,
            -0.23835,
            0.2553,
            0.3389,
            0.22485,
            0.3818,
            0.1909
        ],
        "2024-03-03": [
            0.49475,
            0.6584,
            0.80545
        ],
        "2024-03-02": [
            0.49905,
            0.68935
        ],
        "2024-03-01": [
            -0.3548,
            0.76225
        ],
        "2024-02-29": [
            0.70095,
            0.4989,
            0.7381
        ],
        "2024-02-28": [
            0.4999,
            0.7459
        ],
        "2024-02-27": [
            0.4995,
            0.267,
            0.336,
            0.28595,
            0.3243,
            0.0
        ],
        "2024-02-26": [
            0.88735,
            0.77815,
            0.7373000000000001,
            0.3715,
            0.6633
        ],
        "2024-02-25": [
            0.76325,
            0.7375499999999999,
            0.0,
            0.5805499999999999
        ],
        "2024-02-24": [
            0.4988,
            0.38625,
            -0.064,
            0.5885
        ],
        "2024-02-23": [
            0.7668999999999999,
            0.9077,
            -0.38155,
            0.1191,
            0.50935,
            0.2553
        ],
        "2024-02-22": [
            0.6466,
            0.7995000000000001,
            -0.40615,
            0.31845,
            0.26335
        ],
        "2024-02-21": [
            0.93495,
            0.49625,
            0.6899500000000001
        ],
        "2024-02-20": [
            0.86725,
            0.8239,
            0.4988,
            0.4993,
            0.3243,
            0.55845
        ],
        "2024-02-19": [
            0.7378,
            0.73765,
            0.8119000000000001,
            0.7407,
            0.3895,
            0.37645,
            0.23835
        ],
        "2024-02-18": [
            0.8891,
            0.68955,
            0.8180000000000001,
            0.3706,
            0.50935
        ],
        "2024-02-17": [
            0.73805,
            0.7197,
            0.7622,
            0.76295
        ],
        "2024-02-16": [
            0.49955,
            0.5889,
            0.87825,
            0.91455,
            0.8545,
            0.7199,
            0.73805,
            0.57425,
            0.4801,
            0.418
        ],
        "2024-02-15": [
            0.3518,
            0.49955,
            0.4993,
            0.48619999999999997,
            0.85795,
            0.58895,
            -0.1935,
            0.2787,
            0.4568,
            0.011099999999999999
        ],
        "2024-02-14": [
            0.68955,
            0.6184000000000001,
            0.3982,
            0.9155500000000001,
            -0.3548,
            0.6673,
            0.73775,
            0.7375499999999999,
            0.148,
            0.2113,
            0.60195
        ],
        "2024-02-13": [
            0.20530000000000004,
            0.4994,
            0.7785500000000001,
            0.4998,
            0.5857,
            0.499
        ]
    },
    {
        "2024-08-08": [
            27.04,
            29.28,
            96208508.0
        ],
        "2024-08-07": [
            27.07,
            26.32,
            75037851.0
        ],
        "2024-08-06": [
            27.05,
            26.59,
            99533637.0
        ],
        "2024-08-05": [
            21.74,
            24.09,
            88022314.0
        ],
        "2024-08-02": [
            24.75,
            24.74,
            55260175.0
        ],
        "2024-08-01": [
            27.02,
            26.08,
            30977925.0
        ],
        "2024-07-31": [
            27.02,
            26.89,
            28782283.0
        ],
        "2024-07-30": [
            27.25,
            26.37,
            31532551.0
        ],
        "2024-07-29": [
            27.56,
            27.08,
            25959472.0
        ],
        "2024-07-26": [
            27,
            27.18,
            27327933.0
        ],
        "2024-07-25": [
            26.04,
            26.63,
            45153454.0
        ],
        "2024-07-24": [
            28.44,
            26.6,
            48499888.0
        ],
        "2024-07-23": [
            28.34,
            28.81,
            30460957.0
        ],
        "2024-07-22": [
            28.93,
            28.46,
            37835426.0
        ],
        "2024-07-19": [
            28.31,
            28.58,
            49501367.0
        ],
        "2024-07-18": [
            28.42,
            28.64,
            76368837.0
        ],
        "2024-07-17": [
            28,
            28.22,
            45049438.0
        ],
        "2024-07-16": [
            28.18,
            28.67,
            58714731.0
        ],
        "2024-07-15": [
            28.42,
            28.67,
            48697669.0
        ],
        "2024-07-12": [
            27.32,
            28.07,
            30648075.0
        ],
        "2024-07-11": [
            28.49,
            27.64,
            61134841.0
        ],
        "2024-07-10": [
            27.5,
            28.42,
            43004953.0
        ],
        "2024-07-09": [
            27.93,
            27.39,
            53048753.0
        ],
        "2024-07-08": [
            27.93,
            27.7,
            58129275.0
        ],
        "2024-07-05": [
            26,
            27.23,
            46483386.0
        ],
        "2024-07-03": [
            25.96,
            25.85,
            18426577.0
        ],
        "2024-07-02": [
            25.84,
            25.83,
            31870993.0
        ],
        "2024-07-01": [
            25.48,
            25.88,
            32300542.0
        ],
        "2024-06-28": [
            25.28,
            25.33,
            38530974.0
        ],
        "2024-06-27": [
            24.1,
            25.22,
            37451316.0
        ],
        "2024-06-26": [
            24.47,
            24.1,
            23717634.0
        ],
        "2024-06-25": [
            24.16,
            24.56,
            29464607.0
        ],
        "2024-06-24": [
            23.44,
            24.16,
            36401292.0
        ],
        "2024-06-21": [
            24.71,
            23.84,
            64762754.0
        ],
        "2024-06-20": [
            26.44,
            25.56,
            65439915.0
        ],
        "2024-06-18": [
            25.15,
            25.82,
            54219773.0
        ],
        "2024-06-17": [
            23.47,
            25.02,
            53000854.0
        ],
        "2024-06-14": [
            23.15,
            23.57,
            26444993.0
        ],
        "2024-06-13": [
            23.85,
            23.27,
            25927568.0
        ],
        "2024-06-12": [
            24.2,
            23.77,
            38363667.0
        ],
        "2024-06-11": [
            23.06,
            23.85,
            30454773.0
        ],
        "2024-06-10": [
            22.75,
            23.13,
            31338537.0
        ],
        "2024-06-07": [
            23.24,
            23.31,
            37075922.0
        ],
        "2024-06-06": [
            22.98,
            23.79,
            60225135.0
        ],
        "2024-06-05": [
            22.48,
            22.96,
            39758570.0
        ],
        "2024-06-04": [
            21.05,
            22.1,
            41749183.0
        ],
        "2024-06-03": [
            21.7,
            21.32,
            33694522.0
        ],
        "2024-05-31": [
            21.79,
            21.68,
            43882167.0
        ],
        "2024-05-30": [
            21.28,
            21.73,
            47434537.0
        ],
        "2024-05-29": [
            20.77,
            20.94,
            24729355.0
        ],
        "2024-05-28": [
            21.06,
            21.05,
            25470893.0
        ],
        "2024-05-24": [
            20.72,
            21.01,
            22098591.0
        ],
        "2024-05-23": [
            21.39,
            20.72,
            36852171.0
        ],
        "2024-05-22": [
            21.23,
            21.17,
            25147818.0
        ],
        "2024-05-21": [
            21.34,
            21.24,
            27905575.0
        ],
        "2024-05-20": [
            21.77,
            21.62,
            35121694.0
        ],
        "2024-05-17": [
            21.78,
            21.76,
            29923677.0
        ],
        "2024-05-16": [
            21.74,
            21.65,
            27340021.0
        ],
        "2024-05-15": [
            21.73,
            21.67,
            39312093.0
        ],
        "2024-05-14": [
            20.95,
            21.44,
            57845479.0
        ],
        "2024-05-13": [
            20.6,
            20.94,
            37375669.0
        ],
        "2024-05-10": [
            21.27,
            20.6,
            59800258.0
        ],
        "2024-05-09": [
            21.49,
            21.14,
            54081693.0
        ],
        "2024-05-08": [
            21.58,
            21.56,
            67578474.0
        ],
        "2024-05-07": [
            21.99,
            21.4,
            160984090.0
        ],
        "2024-05-06": [
            24.37,
            25.21,
            175758079.0
        ],
        "2024-05-03": [
            23.48,
            23.33,
            55873236.0
        ],
        "2024-05-02": [
            22.6,
            22.55,
            30209611.0
        ],
        "2024-05-01": [
            21.93,
            22.12,
            34617047.0
        ],
        "2024-04-30": [
            22.77,
            21.97,
            30202437.0
        ],
        "2024-04-29": [
            22.75,
            22.83,
            29851273.0
        ],
        "2024-04-26": [
            22.05,
            22.52,
            33059102.0
        ],
        "2024-04-25": [
            20.82,
            21.71,
            26112355.0
        ],
        "2024-04-24": [
            22.05,
            21.59,
            33459368.0
        ],
        "2024-04-23": [
            21.25,
            21.64,
            36187391.0
        ],
        "2024-04-22": [
            20.72,
            20.97,
            31778596.0
        ],
        "2024-04-19": [
            20.98,
            20.47,
            39439259.0
        ],
        "2024-04-18": [
            21.25,
            21.13,
            34408319.0
        ],
        "2024-04-17": [
            22.01,
            21.31,
            29993011.0
        ],
        "2024-04-16": [
            21.59,
            21.88,
            33785096.0
        ],
        "2024-04-15": [
            22.79,
            21.9,
            38069669.0
        ],
        "2024-04-12": [
            22.7,
            22.67,
            36764458.0
        ],
        "2024-04-11": [
            22.65,
            22.84,
            26399380.0
        ],
        "2024-04-10": [
            22.22,
            22.42,
            28642932.0
        ],
        "2024-04-09": [
            23.01,
            22.81,
            27724525.0
        ],
        "2024-04-08": [
            23.08,
            23,
            25022708.0
        ],
        "2024-04-05": [
            22.42,
            22.96,
            38716824.0
        ],
        "2024-04-04": [
            23.82,
            22.48,
            64995295.0
        ],
        "2024-04-03": [
            22.44,
            22.7,
            30357412.0
        ],
        "2024-04-02": [
            22,
            22.72,
            39770573.0
        ],
        "2024-04-01": [
            22.98,
            22.86,
            41000029.0
        ],
        "2024-03-28": [
            24.17,
            23.01,
            70008165.0
        ],
        "2024-03-27": [
            25,
            24.51,
            38600086.0
        ],
        "2024-03-26": [
            24.76,
            24.89,
            43610464.0
        ],
        "2024-03-25": [
            24.12,
            24.51,
            29255903.0
        ],
        "2024-03-22": [
            24.2,
            24.18,
            25453029.0
        ],
        "2024-03-21": [
            25.3,
            24.49,
            37099608.0
        ],
        "2024-03-20": [
            23.77,
            24.57,
            39673774.0
        ],
        "2024-03-19": [
            23.5,
            23.8,
            43247249.0
        ],
        "2024-03-18": [
            23.77,
            24,
            44078313.0
        ],
        "2024-03-15": [
            23.85,
            23.49,
            61420999.0
        ],
        "2024-03-14": [
            24.83,
            24.43,
            49214784.0
        ],
        "2024-03-13": [
            24.7,
            25,
            59712992.0
        ],
        "2024-03-12": [
            25.57,
            24.7,
            75202613.0
        ],
        "2024-03-11": [
            25.89,
            25.35,
            60829269.0
        ],
        "2024-03-08": [
            27.19,
            26.04,
            84256124.0
        ],
        "2024-03-07": [
            27.01,
            26.46,
            117519319.0
        ],
        "2024-03-06": [
            25.75,
            26.16,
            207386942.0
        ],
        "2024-03-05": [
            23.96,
            23.81,
            49542272.0
        ],
        "2024-03-04": [
            24.4,
            24.04,
            64216031.0
        ],
        "2024-03-01": [
            25.3,
            24.93,
            64794407.0
        ],
        "2024-02-29": [
            24.81,
            25.08,
            62753300.0
        ],
        "2024-02-28": [
            24.52,
            24.42,
            47313982.0
        ],
        "2024-02-27": [
            23.76,
            24.53,
            64967421.0
        ],
        "2024-02-26": [
            23.03,
            23.56,
            46499481.0
        ],
        "2024-02-23": [
            23.53,
            22.97,
            48840765.0
        ],
        "2024-02-22": [
            23.77,
            23.59,
            64382647.0
        ],
        "2024-02-21": [
            22.3,
            22.74,
            60411461.0
        ],
        "2024-02-20": [
            23.84,
            23.4,
            93374349.0
        ],
        "2024-02-16": [
            24.96,
            24.44,
            65498227.0
        ],
        "2024-02-15": [
            25.04,
            25.41,
            70544321.0
        ],
        "2024-02-14": [
            24.15,
            25.19,
            97227926.0
        ],
        "2024-02-13": [
            23.53,
            24.01,
            102293322.0
        ],
        "2024-02-12": [
            23.91,
            25.05,
            108173046.0
        ]
    },
    [
        "PLTR, the stock ticker for Palantir Technologies, is a data analytics company specializing in software for government and commercial clients. \n",
        "Palantir Technologies (PLTR) makes money by providing data analytics software and services to government and commercial clients for decision-making and operational efficiency. \n",
        "Palantir Technologies (PLTR) faces competition from companies like **Microsoft, Google, Amazon Web Services, and C3.ai** in the data analytics and artificial intelligence space. \n",
        "PLTR stock has experienced a generally downward trend over the past 30 days, with some periods of volatility and minor rallies interspersed within the overall decline. \n"
    ]
]